{
    "Home": "ပင်မစာမျက်နှာ",
    "Terms Of Sevice": "ဝန်ဆောင်မှုဆိုင်ရာ သဘောတူညီချက်များ",
    "Password": "စကားဝှက်",
    "Sign Up": "အကောင့်ဖွင့်ရန်",
    "Sign In": "အကောင့်ဝင်ရန်",
    "Login ": "ဝင်ရောက်ရန်",
    "Logout": "ထွက်ရန်",
    "Contact Us": "ဆက်သွယ်ရန်",
    "Upload Post": "ကြော်ငြာတင်ရန်",
    "Show All": "အားလုံးပြပါ",
    "Search": "ရှာဖွေပါ",
    "Select Option": "ရောင်း/ငှား",
    "Rent": "အငှား",
    "Sale": "အရောင်း",
    "Select Region": "ပြည်နယ်နှင့် တိုင်းဒေသကြီး",
    "Select Township": "မြို့နယ်",
    "Select Type": "အိမ်အမျိုးအစား",
    "View Details": "အသေးစိတ်ကြည့်ရန်",
    "Call": "ဖုန်းဆက်ရန်",
    "Ks": "ကျပ်",
    "For Rent": " ငှားရန်",
    "For Sale": "ရောင်းရန်",
    "Price(From)": "ဈေးနှုန်းအနည်း",
    "Price(To)": "ဈေးနှုန်းအများ",
    "100,000": "၁ သိန်း",
    "200,000": "၂ သိန်း",
    "300,000": "၃ သိန်း",
    "400,000": "၄ သိန်း",
    "500,000": "၅ သိန်း",
    "600,000": "၆ သိန်း",
    "Post Registration Form": "",
    "Region": "",
    "Township": "",
    "Property": "",
    "Title": "",
    "Address": "",
    "Phone": "",
    "Area": "",
    "Cover Photo": "",
    "Photos": "",
    "Room": "",
    "Bath Room": "",
    "Description": "",
    "I agree to all ": " ",
    "Post has successfully created": "",
    "Please wait for approve!": "",
    "Please fill this field.": "",
    "Dashboard": "",
    "Posts": "",
    "User Profile": ""
}